LICENSE
sortables/__init__.py
sortables/dictionaries.py
sortables/factory.py
sortables/series.py
sortables-0.1.1.dist-info/LICENSE
sortables-0.1.1.dist-info/WHEEL
sortables-0.1.1.dist-info/METADATA
sortables-0.1.1.dist-info/RECORD
