Metadata-Version: 2.1
Name: sortables
Version: 0.1.1
Summary: sanely sortable Python data structures
Home-page: https://github.com/scott2b/sortables
Keywords: sort,sorting,data structures,dict,tuple,list,set
Author: Scott Bradley
Author-email: scott@scott2b.com
Requires-Python: >=3.7,<4.0
Classifier: Development Status :: 3 - Alpha
Classifier: Intended Audience :: Developers
Classifier: License :: OSI Approved :: MIT License
Classifier: Programming Language :: Python
Classifier: Programming Language :: Python :: 3
Classifier: Programming Language :: Python :: 3.7
Classifier: Topic :: Software Development :: Libraries
Classifier: Topic :: Software Development :: Libraries :: Python Modules
Project-URL: Repository, https://github.com/scott2b/sortables
